delivery_engine_client/__init__.py
delivery_engine_client/api_client.py
delivery_engine_client/api_response.py
delivery_engine_client/configuration.py
delivery_engine_client/exceptions.py
delivery_engine_client/py.typed
delivery_engine_client/rest.py
delivery_engine_client/api/__init__.py
delivery_engine_client/api/deliveries_api.py
delivery_engine_client/api/health_api.py
delivery_engine_client/models/__init__.py
delivery_engine_client/models/deliver_message_response.py
delivery_engine_client/models/http_validation_error.py
delivery_engine_client/models/message.py
delivery_engine_client/models/validation_error.py
delivery_engine_client/models/validation_error_loc_inner.py
delivery_engine_client-1.0.0.dist-info/METADATA
delivery_engine_client-1.0.0.dist-info/WHEEL
delivery_engine_client-1.0.0.dist-info/top_level.txt
delivery_engine_client-1.0.0.dist-info/RECORD
